{
  "WORD":"boy",
  "IPA":"/bɔɪ/",
  "CONJUGATES":"boys | boy's | boys'",
  "ETYMOLOGY":"From Middle English boi (servant, rascal, youth), origin uncertain, possibly Germanic (Frisian or Low German).",
  "SINCE":"c. 13th Century",
  "MEANINGS":[
    {
      "PATTERN":"[sb] (male child)",
      "POS":"n. countable",
      "POS_TIP":"noun, countable",
      "TAGS":[
        "core word",
        "common"
      ],
      "DEF_EN":"A male child or young man.",
      "DEF_ZH":"男性儿童或少年。",
      "SENT_EN":"Their youngest child is a curious six-year-old boy.",
      "SENT_ZH":"他们最小的孩子是个好奇的六岁男孩。",
      "RELATED":[
        {
          "T":"synonyms",
          "V":[
            "lad",
            "kid",
            "youth",
            "chap"
          ]
        },
        {
          "T":"antonyms",
          "V":[
            "girl"
          ]
        },
        {
          "T":"related",
          "V":[
            "man",
            "child"
          ]
        }
      ]
    },
    {
      "PATTERN":"[sb] (adult male, friend)",
      "POS":"n. countable",
      "POS_TIP":"noun, countable",
      "TAGS":[
        "informal",
        "slang"
      ],
      "DEF_EN":"Informal reference to a man, especially a friend, male colleague, or member of a group (often used in the plural, 'the boys').",
      "DEF_ZH":"对男性（尤指朋友、同事或团体成员）的非正式称呼（常用于复数形式“the boys”）。",
      "SENT_EN":"We're heading down to the pub with the boys after work.",
      "SENT_ZH":"我们下班后要和伙计们去酒吧。",
      "RELATED":[
        {
          "T":"synonyms",
          "V":[
            "guy",
            "dude",
            "mate",
            "fella"
          ]
        }
      ]
    },
    {
      "PATTERN":"[sb] (servant, subordinate)",
      "POS":"n. countable",
      "POS_TIP":"noun, countable",
      "TAGS":[
        "dated",
        "offensive",
        "historical"
      ],
      "DEF_EN":"A dated and often offensive term used, especially historically in colonial or racist contexts, to refer to a male servant, slave, or subordinate of any age.",
      "DEF_ZH":"（过时且常带冒犯性的）指男性仆人、奴隶或下属，不论年龄，尤指在殖民或种族主义背景下。",
      "SENT_EN":"The practice of calling adult employees 'boy' is considered deeply offensive and demeaning.",
      "SENT_ZH":"称呼成年雇员为“boy”的做法被认为是带有深刻冒犯性和贬低性的。",
      "RELATED":[]
    },
    {
      "PATTERN":"(exclamation)",
      "POS":"interjection",
      "POS_TIP":"exclamatory word or phrase",
      "TAGS":[
        "informal",
        "exclamatory"
      ],
      "DEF_EN":"An exclamation used to express excitement, surprise, disbelief, or emphasis.",
      "DEF_ZH":"（用于表达兴奋、惊讶、怀疑或强调的感叹词）哎呀；天哪。",
      "SENT_EN":"Oh boy, I can't believe we won the lottery!",
      "SENT_ZH":"哎呀，我简直不敢相信我们中彩票了！",
      "RELATED":[
        {
          "T":"synonyms",
          "V":[
            "wow",
            "gosh",
            "gee"
          ]
        }
      ]
    }
  ],
  "REGISTER":"Highly common in general conversation, literature, and media. Note that usage in reference to adult males (especially Meaning 3) can be highly contextual and often offensive."
}