{
  "WORD":"fairy",
  "IPA":"/ˈfɛəri/",
  "CONJUGATES":"fairies",
  "ETYMOLOGY":"From Old French *faerie* ('realm of the *fae*', 'enchantment'), from *fae* ('fairy'), from Vulgar Latin *Fata* (singular of *Fatae*, 'the Fates', Roman goddesses of destiny). The sense shifted from 'enchantment' to 'a mythical being' over time.",
  "SINCE":"Late Middle English (late 13th century)",
  "MEANINGS":[
    {
      "PATTERN":"[a/the] fairy",
      "POS":"noun",
      "POS_TIP":"A word that represents a person, place, thing, or idea.",
      "TAGS":[
        "core word",
        "common",
        "mythology",
        "folklore"
      ],
      "DEF_EN":"A small, imaginary being of human form that has magical powers, typically depicted with wings.",
      "DEF_ZH":"一种虚构的、具有魔法力量的微小人形生物，通常被描绘成有翅膀。",
      "SENT_EN":"Children often enjoy stories about good fairies and evil witches.",
      "SENT_ZH":"孩子们通常喜欢关于善良仙女和邪恶巫婆的故事。",
      "RELATED":[
        {
          "T":"synonyms",
          "V":[
            "pixie",
            "sprite",
            "elf",
            "nymph"
          ]
        },
        {
          "T":"related",
          "V":[
            "folklore",
            "myth",
            "enchantment"
          ]
        }
      ]
    },
    {
      "PATTERN":"[a] fairy",
      "POS":"noun",
      "POS_TIP":"A word that represents a person, place, thing, or idea.",
      "TAGS":[
        "informal",
        "offensive",
        "derogatory"
      ],
      "DEF_EN":"(Offensive, informal) A derogatory term for a homosexual man.",
      "DEF_ZH":"(贬义，非正式) 对同性恋男性的蔑称。",
      "SENT_EN":"This term is considered highly offensive and should not be used.",
      "SENT_ZH":"这个词被认为是带有强烈冒犯性的，不应使用。",
      "RELATED":[]
    },
    {
      "PATTERN":"fairy [sth] | [sth] is fairy-like",
      "POS":"adjective",
      "POS_TIP":"A word that describes or modifies a noun or pronoun.",
      "TAGS":[
        "descriptive",
        "poetic"
      ],
      "DEF_EN":"Resembling or characteristic of a fairy; delicate, ethereal, or enchanting.",
      "DEF_ZH":"像仙女般的；精致、飘逸或迷人的。",
      "SENT_EN":"The small, intricate flowers had a fairy-like beauty.",
      "SENT_ZH":"那些小巧精致的花朵有着仙女般的美丽。",
      "RELATED":[
        {
          "T":"synonyms",
          "V":[
            "ethereal",
            "delicate",
            "enchanting",
            "magical"
          ]
        },
        {
          "T":"related",
          "V":[
            "fairy tale",
            "fantasy"
          ]
        }
      ]
    }
  ],
  "REGISTER":"Common (for mythical creature), informal and offensive (for derogatory term), literary (for adjective)."
}