{
  "WORD":"glaring",
  "IPA":"/ˈɡlɛərɪŋ/",
  "CONJUGATES":"glaring (adjective) | more glaring (comparative) | most glaring (superlative)",
  "ETYMOLOGY":"From Middle English *glaren* 'to shine, to stare fiercely', possibly of Germanic origin (compare Old Norse *glar* 'glass, glitter'). The adjectival use 'conspicuously obvious' developed from the idea of something 'staring one in the face'.",
  "SINCE":"Early 17th century",
  "MEANINGS":[
    {
      "PATTERN":"glaring [mistake/omission/injustice]",
      "POS":"adjective",
      "POS_TIP":"An adjective describes or modifies a noun or pronoun.",
      "TAGS":[
        "core word",
        "common",
        "descriptive"
      ],
      "DEF_EN":"Very obvious and difficult to ignore; flagrant or conspicuous.",
      "DEF_ZH":"极其明显而难以忽视的；昭然若揭的，公然的。",
      "SENT_EN":"There was a glaring omission in the company's financial report.",
      "SENT_ZH":"公司财务报告中有一个明显的遗漏。",
      "RELATED":[
        {
          "T":"synonyms",
          "V":[
            "obvious",
            "flagrant",
            "conspicuous",
            "blatant",
            "patent"
          ]
        },
        {
          "T":"antonyms",
          "V":[
            "subtle",
            "hidden",
            "minor",
            "insignificant"
          ]
        }
      ]
    },
    {
      "PATTERN":"glaring [light/sun]",
      "POS":"adjective",
      "POS_TIP":"An adjective describes or modifies a noun or pronoun.",
      "TAGS":[
        "core word",
        "common",
        "descriptive"
      ],
      "DEF_EN":"Shining with a strong, unpleasant, or dazzling light.",
      "DEF_ZH":"发出刺眼、令人不快或耀眼的光。",
      "SENT_EN":"The glaring sun made it hard to see the road ahead.",
      "SENT_ZH":"刺眼的阳光让人很难看清前面的路。",
      "RELATED":[
        {
          "T":"synonyms",
          "V":[
            "dazzling",
            "blinding",
            "harsh",
            "intense"
          ]
        },
        {
          "T":"antonyms",
          "V":[
            "dim",
            "soft",
            "faint",
            "mellow"
          ]
        }
      ]
    },
    {
      "PATTERN":"[sb] gives a glaring look",
      "POS":"adjective",
      "POS_TIP":"An adjective describes or modifies a noun or pronoun. In this context, it is often a present participle used adjectivally.",
      "TAGS":[
        "common",
        "descriptive"
      ],
      "DEF_EN":"(Of eyes or a look) fierce or angry.",
      "DEF_ZH":"（指眼神或表情）凶猛的，愤怒的。",
      "SENT_EN":"He gave her a glaring stare after her rude comment.",
      "SENT_ZH":"在她无礼的评论后，他怒视着她。",
      "RELATED":[
        {
          "T":"synonyms",
          "V":[
            "fierce",
            "angry",
            "furious",
            "hostile",
            "scowling"
          ]
        },
        {
          "T":"antonyms",
          "V":[
            "gentle",
            "mild",
            "friendly",
            "approving"
          ]
        }
      ]
    }
  ],
  "REGISTER":"General"
}