{
  "WORD":"imbalance",
  "IPA":"/ɪmˈbæləns/",
  "CONJUGATES":"imbalances (plural noun)",
  "ETYMOLOGY":"From Latin 'in-' (not, opposite of) + 'balance' (from Old French 'balance', ultimately from Latin 'bilanx' 'having two scales').",
  "SINCE":"Mid-17th century",
  "MEANINGS":[
    {
      "PATTERN":"an imbalance [between A and B] | an imbalance [in sth]",
      "POS":"noun",
      "POS_TIP":"A word referring to a person, place, thing, quality, or idea. Can be counted or not counted.",
      "TAGS":[
        "core word",
        "common"
      ],
      "DEF_EN":"A state or condition in which different things are not equal or in the correct proportions; a lack of balance.",
      "DEF_ZH":"不同事物之间不相等或比例不正确的状态或情况；失去平衡。",
      "SENT_EN":"There is a significant imbalance between imports and exports.",
      "SENT_ZH":"进出口之间存在着显著的不平衡。",
      "RELATED":[
        {
          "T":"synonyms",
          "V":[
            "disproportion",
            "disparity",
            "inequality",
            "asymmetry"
          ]
        },
        {
          "T":"antonyms",
          "V":[
            "balance",
            "equilibrium",
            "proportion",
            "parity"
          ]
        }
      ]
    },
    {
      "PATTERN":"a hormonal imbalance | a chemical imbalance",
      "POS":"noun",
      "POS_TIP":"A word referring to a person, place, thing, quality, or idea. Can be counted or not counted.",
      "TAGS":[
        "technical",
        "medical"
      ],
      "DEF_EN":"An unequal distribution of substances or functions within a biological or chemical system, often leading to health issues.",
      "DEF_ZH":"生物或化学系统中物质或功能的分布不均，常导致健康问题。",
      "SENT_EN":"Her mood swings were attributed to a hormonal imbalance.",
      "SENT_ZH":"她的情绪波动被归因于荷尔蒙失衡。",
      "RELATED":[
        {
          "T":"related",
          "V":[
            "dysfunction",
            "deficiency",
            "excess"
          ]
        }
      ]
    }
  ],
  "REGISTER":"Common; can be used in general, scientific, economic, and medical contexts."
}