{
  "WORD":"infusion",
  "IPA":"/ɪnˈfjuːʒən/",
  "CONJUGATES":"infusions (plural)",
  "ETYMOLOGY":"From Latin *infusionem* (nominative *infusio*), from *infundere* 'to pour in', from *in-* 'into' + *fundere* 'to pour'.",
  "SINCE":"Late Middle English (circa 14th century)",
  "MEANINGS":[
    {
      "PATTERN":"an infusion of [sth]",
      "POS":"noun",
      "POS_TIP":"A word that refers to a person, place, thing, or idea.",
      "TAGS":[
        "core word",
        "abstract",
        "formal"
      ],
      "DEF_EN":"The act or process of introducing a new element, quality, or substance into something.",
      "DEF_ZH":"将新元素、品质或物质注入或引入某事物的行为或过程。",
      "SENT_EN":"The small business benefited from a sudden infusion of capital.",
      "SENT_ZH":"这家小企业受益于突然注入的资金。",
      "RELATED":[
        {
          "T":"synonyms",
          "V":[
            "introduction",
            "injection",
            "instillation",
            "impartation",
            "introduction"
          ]
        },
        {
          "T":"related",
          "V":[
            "infuse",
            "inject",
            "instill",
            "impart"
          ]
        }
      ]
    },
    {
      "PATTERN":"an infusion of [liquid/substance]",
      "POS":"noun",
      "POS_TIP":"A word that refers to a person, place, thing, or idea.",
      "TAGS":[
        "medical",
        "culinary",
        "countable"
      ],
      "DEF_EN":"A liquid preparation made by steeping a substance (such as herbs or tea) in water or another liquid; or (medical) a liquid administered slowly into the body, typically into a vein.",
      "DEF_ZH":"通过将物质（如草药或茶叶）浸泡在水或其他液体中制成的液体制剂；或（医学）缓慢注入体内，通常是静脉的液体。",
      "SENT_EN":"She enjoyed a warm herbal infusion to aid digestion. The patient required an intravenous infusion of antibiotics.",
      "SENT_ZH":"她喜欢喝一杯温暖的草药浸剂来帮助消化。病人需要静脉输注抗生素。",
      "RELATED":[
        {
          "T":"synonyms",
          "V":[
            "brew",
            "decoction",
            "tincture",
            "drip",
            "transfusion"
          ]
        },
        {
          "T":"related",
          "V":[
            "infuse",
            "tea",
            "intravenous",
            "extract"
          ]
        }
      ]
    }
  ],
  "REGISTER":"Formal, medical, culinary, general"
}