{
  "WORD":"longevity",
  "IPA":"/lɒnˈdʒɛvɪti/",
  "CONJUGATES":"None",
  "ETYMOLOGY":"From Latin longaevitas, from longaevus 'long-lived' (from longus 'long' + aevum 'age')",
  "SINCE":"Mid-17th century",
  "MEANINGS":[
    {
      "PATTERN":"longevity",
      "POS":"n",
      "POS_TIP":"noun",
      "TAGS":[
        "core word",
        "common",
        "formal"
      ],
      "DEF_EN":"Long existence or service; a long duration of life.",
      "DEF_ZH":"长寿；长久存在或服务；寿命长久。",
      "SENT_EN":"The company's longevity in the market is a testament to its adaptable business model.",
      "SENT_ZH":"这家公司在市场上的长久存在证明了其灵活的商业模式。",
      "RELATED":[
        {
          "T":"synonyms",
          "V":[
            "durability",
            "endurance",
            "persistence",
            "long life"
          ]
        },
        {
          "T":"antonyms",
          "V":[
            "brevity",
            "ephemerality",
            "shortness"
          ]
        }
      ]
    }
  ],
  "REGISTER":"Formal or neutral, often used in scientific, health, or business contexts."
}