{
  "WORD":"rank",
  "IPA":"/ræŋk/",
  "CONJUGATES":"ranks | ranking | ranked | ranker | rankest",
  "ETYMOLOGY":"Derived partly from Old English 'ranc' (proud, strong, vigorous) and partly from Old French 'ranc' (row, line, position), merging into modern usage in the Middle English period.",
  "SINCE":"c. 1300s",
  "MEANINGS":[
    {
      "PATTERN":"[sb/sth]'s rank\nthe rank of [sb/sth]",
      "POS":"n",
      "POS_TIP":"noun",
      "TAGS":[
        "core word",
        "common"
      ],
      "DEF_EN":"A position, grade, or classification within a specific hierarchy or sequence.",
      "DEF_ZH":"等级; 级别; 地位; 职衔。",
      "SENT_EN":"He holds the rank of Captain in the army.",
      "SENT_ZH":"他在军队中担任上尉军衔。",
      "RELATED":[
        {
          "T":"synonyms",
          "V":[
            "status",
            "grade",
            "level",
            "position"
          ]
        },
        {
          "T":"related",
          "V":[
            "hierarchy",
            "standing"
          ]
        }
      ]
    },
    {
      "PATTERN":"rank [sth] (vtr)\n[sth] ranks (vi)",
      "POS":"vtr | vi",
      "POS_TIP":"transitive verb | intransitive verb",
      "TAGS":[
        "core word",
        "common"
      ],
      "DEF_EN":"To assign a specific position or place to something or someone in relation to others, often on a scale.",
      "DEF_ZH":"排名; 排定等级; 评估。",
      "SENT_EN":"The magazine ranked the film as the best of the year.",
      "SENT_ZH":"该杂志将这部电影评为年度最佳。",
      "RELATED":[
        {
          "T":"synonyms",
          "V":[
            "classify",
            "rate",
            "grade",
            "assess"
          ]
        }
      ]
    },
    {
      "PATTERN":"the ranks (n pl)",
      "POS":"n pl",
      "POS_TIP":"plural noun",
      "TAGS":[
        "military",
        "idiomatic"
      ],
      "DEF_EN":"The ordinary members of an organization, especially military personnel who are not officers.",
      "DEF_ZH":"(尤指军队的) 普通士兵; 群众，普通成员。",
      "SENT_EN":"He rose from the ranks to become a general.",
      "SENT_ZH":"他从普通士兵晋升为将军。",
      "RELATED":[
        {
          "T":"synonyms",
          "V":[
            "foot soldiers",
            "enlisted men",
            "members"
          ]
        }
      ]
    },
    {
      "PATTERN":"rank [adj]",
      "POS":"adj",
      "POS_TIP":"adjective",
      "TAGS":[
        "old word",
        "figurative",
        "negative connotation"
      ],
      "DEF_EN":"Having a strong, unpleasant smell or taste; vigorous and abundant, often excessively so (e.g., of weeds).",
      "DEF_ZH":"恶臭的; 难闻的; 过于茂盛的; (味道) 浓烈的。",
      "SENT_EN":"The air was filled with a rank, swampy odor.",
      "SENT_ZH":"空气中弥漫着一股沼泽地特有的恶臭。",
      "RELATED":[
        {
          "T":"synonyms",
          "V":[
            "fetid",
            "putrid",
            "foul",
            "pungent"
          ]
        },
        {
          "T":"antonyms",
          "V":[
            "fragrant",
            "mild"
          ]
        }
      ]
    }
  ],
  "REGISTER":"General usage across formal, academic, military, and colloquial contexts."
}