{
  "WORD":"salmon",
  "IPA":"/ˈsæmən/",
  "CONJUGATES":"singular: salmon | plural: salmon",
  "ETYMOLOGY":"From Middle English samoun, from Anglo-Norman salmun, saumon, from Latin salmō, salmōnem 'salmon'.",
  "SINCE":"Before 12th century",
  "MEANINGS":[
    {
      "PATTERN":"salmon",
      "POS":"noun",
      "POS_TIP":"noun: a word that refers to a person, place, thing, event, substance, or quality.",
      "TAGS":[
        "core word",
        "common",
        "fish"
      ],
      "DEF_EN":"A large, edible, anadromous fish of the family Salmonidae, typically with silvery scales and pinkish-orange flesh, that breeds in freshwater and spends most of its life in the sea.",
      "DEF_ZH":"一种大型可食用的洄游鱼类，属于鲑科，通常有银色的鱼鳞和粉橙色的鱼肉，在淡水中繁殖，一生大部分时间在海中度过。",
      "SENT_EN":"We had grilled salmon for dinner last night.",
      "SENT_ZH":"我们昨晚晚餐吃了烤三文鱼。",
      "RELATED":[
        {
          "T":"related",
          "V":[
            "trout",
            "char",
            "sushi",
            "aquaculture"
          ]
        }
      ]
    },
    {
      "PATTERN":"salmon",
      "POS":"adjective | noun",
      "POS_TIP":"adjective: a word that describes or modifies a noun or pronoun. | noun: a word that refers to a person, place, thing, event, substance, or quality.",
      "TAGS":[
        "common",
        "color"
      ],
      "DEF_EN":"A pale orange or pinkish-orange color, resembling the flesh of salmon.",
      "DEF_ZH":"一种浅橙色或粉橙色，类似于三文鱼肉的颜色。",
      "SENT_EN":"She painted her room a lovely shade of salmon.",
      "SENT_ZH":"她把房间漆成了漂亮的鲑鱼粉色。",
      "RELATED":[
        {
          "T":"synonyms",
          "V":[
            "salmon pink",
            "coral"
          ]
        },
        {
          "T":"related",
          "V":[
            "pink",
            "orange"
          ]
        }
      ]
    }
  ],
  "REGISTER":"General"
}