{
  "WORD":"scare",
  "IPA":"/skɛər/",
  "CONJUGATES":"scares | scared | scaring",
  "ETYMOLOGY":"From Middle English 'skeren' (to frighten), likely adapted from Old Norse 'skirra' (to avert, frighten), related to 'skjarr' (timid, shy).",
  "SINCE":"c. 1300s (Late Middle English)",
  "MEANINGS":[
    {
      "PATTERN":"scare [sb]\nscare [sth]",
      "POS":"vtr",
      "POS_TIP":"Transitive verb (a verb that takes one or more objects)",
      "TAGS":[
        "core word",
        "common"
      ],
      "DEF_EN":"To fill with sudden, great fear or alarm; frighten.",
      "DEF_ZH":"使惊恐；吓唬；引起突然的恐惧。",
      "SENT_EN":"The loud crash outside scared the children.",
      "SENT_ZH":"外面巨大的撞击声吓到了孩子们。",
      "RELATED":[
        {
          "T":"synonyms",
          "V":[
            "frighten",
            "terrify",
            "startle",
            "alarm"
          ]
        },
        {
          "T":"antonyms",
          "V":[
            "calm",
            "soothe",
            "comfort"
          ]
        }
      ]
    },
    {
      "PATTERN":"scare (off\naway) [sth]",
      "POS":"vphr",
      "POS_TIP":"Phrasal verb (a combination of a verb and an adverb or a preposition, or both)",
      "TAGS":[
        "common"
      ],
      "DEF_EN":"To cause someone or something to leave or abandon a plan by making them afraid.",
      "DEF_ZH":"吓跑；使（某人或某物）因害怕而离开或放弃。",
      "SENT_EN":"The police presence scared off the potential vandals.",
      "SENT_ZH":"警察的出现吓跑了潜在的破坏者。",
      "RELATED":[
        {
          "T":"synonyms",
          "V":[
            "deter",
            "chase away",
            "repel"
          ]
        }
      ]
    },
    {
      "PATTERN":"a scare",
      "POS":"n",
      "POS_TIP":"Noun (a word used to identify any of a class of people, places, or things, or to name a particular one of these)",
      "TAGS":[
        "common",
        "countable"
      ],
      "DEF_EN":"A sudden feeling of alarm or fright; a temporary period of fear or panic.",
      "DEF_ZH":"惊吓；恐慌；（短暂的）惊恐感。",
      "SENT_EN":"We had a health scare when the test results came back abnormal.",
      "SENT_ZH":"当检测结果显示异常时，我们虚惊了一场。",
      "RELATED":[
        {
          "T":"synonyms",
          "V":[
            "fright",
            "shock",
            "alarm",
            "panic"
          ]
        }
      ]
    }
  ],
  "REGISTER":"General Conversation and Journalism",
  "POS_TIP":{
    "vtr":"Transitive verb",
    "vphr":"Phrasal verb",
    "n":"Noun"
  }
}