{
  "WORD":"situation",
  "IPA":"/ˌsɪtʃuˈeɪʃən/",
  "CONJUGATES":"situations",
  "ETYMOLOGY":"From Late Middle English (circa 1380s), via Old French situation or Medieval Latin situatio(n-), derived from Latin situs, meaning 'site, position'.",
  "SINCE":"c. 1380",
  "MEANINGS":[
    {
      "PATTERN":"a situation\nthe situation",
      "POS":"noun",
      "POS_TIP":"countable or uncountable noun",
      "TAGS":[
        "core word",
        "common",
        "abstract"
      ],
      "DEF_EN":"A set of circumstances in which one finds oneself; a state of affairs or surrounding conditions.",
      "DEF_ZH":"形势；局面；情况；境况。",
      "SENT_EN":"We need to assess the seriousness of the current political situation.",
      "SENT_ZH":"我们需要评估当前政治局势的严重性。",
      "RELATED":[
        {
          "T":"synonyms",
          "V":[
            "circumstance",
            "condition",
            "state of affairs",
            "predicament",
            "context"
          ]
        },
        {
          "T":"related",
          "V":[
            "scenario",
            "contingency"
          ]
        }
      ]
    },
    {
      "PATTERN":"the situation of [sth]",
      "POS":"noun",
      "POS_TIP":"uncountable noun",
      "TAGS":[
        "formal",
        "spatial"
      ],
      "DEF_EN":"The location and position of something, especially a building, town, or feature.",
      "DEF_ZH":"（地点或城镇的）位置，选址；所在地。",
      "SENT_EN":"The charming situation of the hotel overlooking the lake contributed to its popularity.",
      "SENT_ZH":"这家酒店俯瞰湖泊的迷人位置，使其广受欢迎。",
      "RELATED":[
        {
          "T":"synonyms",
          "V":[
            "location",
            "position",
            "site",
            "setting"
          ]
        }
      ]
    },
    {
      "PATTERN":"a situation",
      "POS":"noun",
      "POS_TIP":"countable noun",
      "TAGS":[
        "dated",
        "employment"
      ],
      "DEF_EN":"A job or post of employment, especially one involving domestic service.",
      "DEF_ZH":"职位；工作（尤指家政或服务性工作）。",
      "SENT_EN":"She was looking for a respectable situation as a housekeeper in a good family.",
      "SENT_ZH":"她正在寻找一份在好家庭里做管家的体面工作。",
      "RELATED":[
        {
          "T":"synonyms",
          "V":[
            "job",
            "post",
            "employment"
          ]
        }
      ]
    }
  ],
  "REGISTER":"General usage, highly common in conversational and formal language."
}