{
  "WORD":"sunburn",
  "IPA":"/ˈsʌnbɜːrn/",
  "CONJUGATES":"sunburns | sunburned | sunburnt | sunburning",
  "ETYMOLOGY":"Compound of 'sun' (from Old English 'sunne') and 'burn' (from Old English 'byrnan' or 'bærnan'). First attested as a compound noun.",
  "SINCE":"c. 1670s",
  "MEANINGS":[
    {
      "PATTERN":"a sunburn | get a sunburn",
      "POS":"n",
      "POS_TIP":"noun: a word that refers to a person, place, thing, event, substance, or quality",
      "TAGS":[
        "core word",
        "common"
      ],
      "DEF_EN":"Redness, pain, or blistering of the skin caused by overexposure to the sun's ultraviolet rays.",
      "DEF_ZH":"皮肤因过度暴露于阳光紫外线而发红、疼痛或起水泡的情况。",
      "SENT_EN":"She got a severe sunburn after spending all day at the beach without sunscreen.",
      "SENT_ZH":"她在海滩上待了一整天没有涂防晒霜，结果晒伤严重。",
      "RELATED":[
        {
          "T":"synonyms",
          "V":[
            "solar erythema"
          ]
        },
        {
          "T":"related",
          "V":[
            "tan",
            "sunstroke"
          ]
        }
      ]
    },
    {
      "PATTERN":"[sb] sunburns | to sunburn [sth]",
      "POS":"v",
      "POS_TIP":"verb: a word or phrase that describes an action, condition, or experience",
      "TAGS":[
        "core word",
        "common"
      ],
      "DEF_EN":"To become or cause to become painfully reddened and damaged by exposure to the sun.",
      "DEF_ZH":"因暴露于阳光下而使皮肤发红疼痛或受损。",
      "SENT_EN":"Be careful not to sunburn your shoulders during your vacation.",
      "SENT_ZH":"度假期间小心不要晒伤你的肩膀。",
      "RELATED":[
        {
          "T":"synonyms",
          "V":[
            "scorch",
            "fry"
          ]
        },
        {
          "T":"antonyms",
          "V":[
            "protect",
            "shade"
          ]
        }
      ]
    }
  ],
  "REGISTER":"General"
}