{
  "WORD":"uproot",
  "IPA":"/ʌpˈruːt/",
  "CONJUGATES":"uproots | uprooted | uprooting",
  "ETYMOLOGY":"From Middle English uprouten; equivalent to up- + root (verb).",
  "SINCE":"Late 14th century",
  "MEANINGS":[
    {
      "PATTERN":"uproot [sth]",
      "POS":"vtr",
      "POS_TIP":"transitive verb: a verb that takes one or more objects",
      "TAGS":[
        "core word",
        "common",
        "literal"
      ],
      "DEF_EN":"To pull (a plant, tree, etc.) out of the ground completely, including its roots.",
      "DEF_ZH":"将（植物、树木等）连根拔起。",
      "SENT_EN":"The strong winds uprooted several old trees during the storm.",
      "SENT_ZH":"强风在暴风雨中连根拔起了好几棵老树。",
      "RELATED":[
        {
          "T":"synonyms",
          "V":[
            "extirpate",
            "deracinate"
          ]
        },
        {
          "T":"antonyms",
          "V":[
            "plant",
            "embed"
          ]
        }
      ]
    },
    {
      "PATTERN":"uproot [sb] / [sth]",
      "POS":"vtr",
      "POS_TIP":"transitive verb: a verb that takes one or more objects",
      "TAGS":[
        "core word",
        "common",
        "figurative"
      ],
      "DEF_EN":"To force someone to leave their home or usual environment and move to another place.",
      "DEF_ZH":"迫使某人离开家园或熟悉的环境，迁移到别处。",
      "SENT_EN":"The war forced many families to uproot themselves and seek refuge elsewhere.",
      "SENT_ZH":"战争迫使许多家庭背井离乡，到别处寻求庇护。",
      "RELATED":[
        {
          "T":"synonyms",
          "V":[
            "displace",
            "relocate",
            "dislodge"
          ]
        },
        {
          "T":"antonyms",
          "V":[
            "settle",
            "establish"
          ]
        }
      ]
    },
    {
      "PATTERN":"uproot [sth]",
      "POS":"vtr",
      "POS_TIP":"transitive verb: a verb that takes one or more objects",
      "TAGS":[
        "common",
        "figurative"
      ],
      "DEF_EN":"To completely destroy or remove something that has been deeply established, such as an idea, custom, or system.",
      "DEF_ZH":"彻底摧毁或消除根深蒂固的事物，例如思想、习俗或制度。",
      "SENT_EN":"The revolution aimed to uproot the old corrupt system.",
      "SENT_ZH":"这场革命旨在彻底铲除旧的腐败制度。",
      "RELATED":[
        {
          "T":"synonyms",
          "V":[
            "eradicate",
            "abolish",
            "eliminate"
          ]
        },
        {
          "T":"antonyms",
          "V":[
            "establish",
            "instill"
          ]
        }
      ]
    }
  ],
  "REGISTER":"general"
}