{
  "WORD":"vapour",
  "IPA":"/'veɪpər/",
  "CONJUGATES":"vapours (plural) | vapor (US spelling)",
  "ETYMOLOGY":"From Middle English vapour, from Anglo-Norman vapour, from Latin vapor ('steam, heat, exhalation').",
  "SINCE":"Mid-14th century",
  "MEANINGS":[
    {
      "PATTERN":"[sth]",
      "POS":"nc",
      "POS_TIP":"noun, countable",
      "TAGS":[
        "core word",
        "scientific",
        "common"
      ],
      "DEF_EN":"A substance diffused or suspended in the air, especially one that is normally liquid or solid at room temperature; the gaseous state of a substance below its critical temperature.",
      "DEF_ZH":"悬浮在空气中的物质，尤指在常温下通常为液体或固体的物质的气态形式；低于临界温度的气态物质。",
      "SENT_EN":"The condensation formed when water vapour touched the cold surface.",
      "SENT_ZH":"当水蒸气接触到冰冷的表面时，形成了冷凝水。",
      "RELATED":[
        {
          "T":"synonyms",
          "V":[
            "steam",
            "mist",
            "gas",
            "fume"
          ]
        },
        {
          "T":"related",
          "V":[
            "vaporize",
            "evaporation"
          ]
        }
      ]
    },
    {
      "PATTERN":"(plural) (literary)",
      "POS":"nc",
      "POS_TIP":"noun, countable",
      "TAGS":[
        "historical",
        "archaic",
        "literary"
      ],
      "DEF_EN":"(Historical or literary) A state of mental depression, melancholy, or nervousness, especially used facetiously referring to the 'vapors' often attributed to women in the 18th and 19th centuries.",
      "DEF_ZH":"（历史或文学）精神沮丧、忧郁或神经质的状态（尤指18、19世纪常归因于女性的“忧郁症”）。",
      "SENT_EN":"She was so delicate that she often suffered from the vapours.",
      "SENT_ZH":"她非常娇弱，经常患上“忧郁症”。",
      "RELATED":[
        {
          "T":"synonyms",
          "V":[
            "melancholy",
            "doldrums",
            "low spirits"
          ]
        }
      ]
    }
  ],
  "REGISTER":"General, Scientific, British English (UK/Commonwealth)"
}