{
  "WORD":"word",
  "IPA":"/wɜːrd/",
  "CONJUGATES":"words (n) | words (v) | worded | wording",
  "ETYMOLOGY":"From Old English word, from Proto-Germanic *wurda, from Proto-Indo-European *wérh₁dʰo-.",
  "SINCE":"Pre-1100s",
  "MEANINGS":[
    {
      "PATTERN":"[a] word | words",
      "POS":"n",
      "POS_TIP":"noun",
      "TAGS":[
        "core word",
        "common"
      ],
      "DEF_EN":"A single unit of language that has meaning and can be spoken or written.",
      "DEF_ZH":"一个具有意义并可以口语或书写的语言单位。",
      "SENT_EN":"She struggled to find the right words to express her feelings.",
      "SENT_ZH":"她努力寻找合适的词语来表达她的感受。",
      "RELATED":[
        {
          "T":"synonyms",
          "V":[
            "term",
            "expression",
            "lexeme"
          ]
        },
        {
          "T":"related",
          "V":[
            "vocabulary",
            "language"
          ]
        }
      ]
    },
    {
      "PATTERN":"a word (with sb)",
      "POS":"n",
      "POS_TIP":"noun",
      "TAGS":[
        "common",
        "idiomatic"
      ],
      "DEF_EN":"A brief conversation, discussion, or statement.",
      "DEF_ZH":"简短的谈话、讨论或声明。",
      "SENT_EN":"Can I have a word with you about the project?",
      "SENT_ZH":"我能和你聊几句关于这个项目的事吗？",
      "RELATED":[
        {
          "T":"synonyms",
          "V":[
            "chat",
            "talk",
            "discussion"
          ]
        }
      ]
    },
    {
      "PATTERN":"word (of sth)",
      "POS":"n",
      "POS_TIP":"noun",
      "TAGS":[
        "common"
      ],
      "DEF_EN":"Information or news.",
      "DEF_ZH":"信息或消息。",
      "SENT_EN":"We received word that the meeting has been postponed.",
      "SENT_ZH":"我们收到消息说会议推迟了。",
      "RELATED":[
        {
          "T":"synonyms",
          "V":[
            "news",
            "information",
            "report"
          ]
        }
      ]
    },
    {
      "PATTERN":"[sb's] word",
      "POS":"n",
      "POS_TIP":"noun",
      "TAGS":[
        "common",
        "idiomatic"
      ],
      "DEF_EN":"A promise or an assurance.",
      "DEF_ZH":"承诺或保证。",
      "SENT_EN":"I give you my word that I will finish the task on time.",
      "SENT_ZH":"我向你保证我会按时完成任务。",
      "RELATED":[
        {
          "T":"synonyms",
          "V":[
            "promise",
            "pledge",
            "assurance"
          ]
        }
      ]
    },
    {
      "PATTERN":"word [sth]",
      "POS":"vt",
      "POS_TIP":"transitive verb",
      "TAGS":[
        "common"
      ],
      "DEF_EN":"To express something in particular words.",
      "DEF_ZH":"用特定的词语表达某事。",
      "SENT_EN":"The contract was carefully worded to avoid any ambiguity.",
      "SENT_ZH":"合同措辞严谨，以避免任何歧义。",
      "RELATED":[
        {
          "T":"synonyms",
          "V":[
            "phrase",
            "express",
            "formulate"
          ]
        }
      ]
    }
  ],
  "REGISTER":"General"
}